[
  {
    "contentsId": 13263,
    "planetId": 4,
    "seriesId": 1435,
    "thumbnailPath": "https://d2nmfrc2pe2bsk.cloudfront.net/1/1671/99666d59-411f-4b20-91ab-f39c1152d7c9.jpg?type=w100",
    "priority": 0,
    "createdAt": "2022-06-10T13:42:30.350Z",
    "updatedAt": "2022-07-27T05:16:43.527Z",
    "paid": false
  },
  {
    "contentsId": 13264,
    "planetId": 4,
    "seriesId": 1435,
    "thumbnailPath": "https://d2nmfrc2pe2bsk.cloudfront.net/1/1671/954512a1-78e5-4d91-a9de-9e7f577c36f7.jpg?type=w100",
    "priority": 1,
    "createdAt": "2022-06-10T13:42:30.466Z",
    "updatedAt": "2022-07-27T05:16:43.529Z",
    "paid": false
  },
  {
    "contentsId": 13265,
    "planetId": 4,
    "seriesId": 1435,
    "thumbnailPath": "https://d2nmfrc2pe2bsk.cloudfront.net/1/1671/c30ec66f-b708-433c-b8b9-3f06d2dc866a.jpg?type=w100",
    "priority": 2,
    "createdAt": "2022-06-10T13:42:30.582Z",
    "updatedAt": "2022-07-27T05:16:43.533Z",
    "paid": false
  },
  {
    "contentsId": 13266,
    "planetId": 4,
    "seriesId": 1435,
    "thumbnailPath": "https://d2nmfrc2pe2bsk.cloudfront.net/1/1671/5546b844-1b2e-43a9-af3b-64fee99899c1.jpg?type=w100",
    "priority": 3,
    "createdAt": "2022-06-10T13:42:30.700Z",
    "updatedAt": "2022-07-27T05:16:43.536Z",
    "paid": false
  },
  {
    "contentsId": 13267,
    "planetId": 4,
    "seriesId": 1435,
    "thumbnailPath": "https://d2nmfrc2pe2bsk.cloudfront.net/1/1671/fed7798b-9a1e-40cb-b2a7-bce44640fd80.jpg?type=w100",
    "priority": 4,
    "createdAt": "2022-06-10T13:42:30.816Z",
    "updatedAt": "2022-07-27T05:16:43.541Z",
    "paid": false
  },
  {
    "contentsId": 13268,
    "planetId": 4,
    "seriesId": 1435,
    "thumbnailPath": "https://d2nmfrc2pe2bsk.cloudfront.net/1/1671/1f856ef3-4217-458d-9121-9f9064f7a5d6.jpg?type=w100",
    "priority": 5,
    "createdAt": "2022-06-10T13:42:30.933Z",
    "updatedAt": "2022-07-27T05:16:43.545Z",
    "paid": false
  },
  {
    "contentsId": 13269,
    "planetId": 4,
    "seriesId": 1435,
    "thumbnailPath": "https://d2nmfrc2pe2bsk.cloudfront.net/1/1671/ff539d30-a2e3-479c-acc9-ce3c4e99b29f.jpg?type=w100",
    "priority": 6,
    "createdAt": "2022-06-10T13:42:31.049Z",
    "updatedAt": "2022-07-27T05:16:43.548Z",
    "paid": false
  },
  {
    "contentsId": 13270,
    "planetId": 4,
    "seriesId": 1435,
    "thumbnailPath": "https://d2nmfrc2pe2bsk.cloudfront.net/1/1671/1a1339b7-3e99-43a7-9f5c-50457ab1f26d.jpg?type=w100",
    "priority": 7,
    "createdAt": "2022-06-10T13:42:31.166Z",
    "updatedAt": "2022-07-27T05:16:43.552Z",
    "paid": false
  },
  {
    "contentsId": 13271,
    "planetId": 4,
    "seriesId": 1435,
    "thumbnailPath": "https://d2nmfrc2pe2bsk.cloudfront.net/1/1671/a45a4631-0006-474b-887c-98db382d7ebd.jpg?type=w100",
    "priority": 8,
    "createdAt": "2022-06-10T13:42:31.282Z",
    "updatedAt": "2022-07-27T05:16:43.555Z",
    "paid": false
  },
  {
    "contentsId": 13272,
    "planetId": 4,
    "seriesId": 1435,
    "thumbnailPath": "https://d2nmfrc2pe2bsk.cloudfront.net/1/1671/44c8ce9f-9460-4e6e-9eae-2ca402f4989b.jpg?type=w100",
    "priority": 9,
    "createdAt": "2022-06-10T13:42:31.398Z",
    "updatedAt": "2022-07-27T05:16:43.559Z",
    "paid": false
  }
]