[
  {
    "contentsId": 3498,
    "planetId": 4,
    "seriesId": 364,
    "thumbnailPath": "https://d2nmfrc2pe2bsk.cloudfront.net/1/1262/1752f8a4-0166-4643-9753-ccdf6a1d53cc.jpg?type=w100",
    "priority": 0,
    "createdAt": "2022-05-24T13:36:42.449Z",
    "updatedAt": "2022-05-24T13:36:42.449Z",
    "paid": false
  },
  {
    "contentsId": 3499,
    "planetId": 4,
    "seriesId": 364,
    "thumbnailPath": "https://d2nmfrc2pe2bsk.cloudfront.net/1/1262/ecf77eeb-2a8b-4a4c-99f9-abe69a9f96bb.jpg?type=w100",
    "priority": 0,
    "createdAt": "2022-05-24T13:36:42.449Z",
    "updatedAt": "2022-05-24T13:36:42.449Z",
    "paid": false
  },
  {
    "contentsId": 3500,
    "planetId": 4,
    "seriesId": 364,
    "thumbnailPath": "https://d2nmfrc2pe2bsk.cloudfront.net/1/1262/f348a961-dd5d-4114-ae21-7999ea22e070.jpg?type=w100",
    "priority": 0,
    "createdAt": "2022-05-24T13:36:42.449Z",
    "updatedAt": "2022-05-24T13:36:42.449Z",
    "paid": false
  },
  {
    "contentsId": 3501,
    "planetId": 4,
    "seriesId": 364,
    "thumbnailPath": "https://d2nmfrc2pe2bsk.cloudfront.net/1/1262/06a92d09-41c5-48c7-a1a3-4704f5895cd5.jpg?type=w100",
    "priority": 0,
    "createdAt": "2022-05-24T13:36:42.449Z",
    "updatedAt": "2022-05-24T13:36:42.449Z",
    "paid": false
  },
  {
    "contentsId": 3502,
    "planetId": 4,
    "seriesId": 364,
    "thumbnailPath": "https://d2nmfrc2pe2bsk.cloudfront.net/1/1262/368b808b-9031-456d-9546-10a7566ae74b.jpg?type=w100",
    "priority": 0,
    "createdAt": "2022-05-24T13:36:42.449Z",
    "updatedAt": "2022-05-24T13:36:42.449Z",
    "paid": false
  },
  {
    "contentsId": 3503,
    "planetId": 4,
    "seriesId": 364,
    "thumbnailPath": "https://d2nmfrc2pe2bsk.cloudfront.net/1/1262/2f3b963b-12fa-4ad6-925b-06e422803cde.jpg?type=w100",
    "priority": 0,
    "createdAt": "2022-05-24T13:36:42.449Z",
    "updatedAt": "2022-05-24T13:36:42.449Z",
    "paid": false
  },
  {
    "contentsId": 3504,
    "planetId": 4,
    "seriesId": 364,
    "thumbnailPath": "https://d2nmfrc2pe2bsk.cloudfront.net/1/1262/7d3745e4-7303-4593-bb70-1805ee989b53.jpg?type=w100",
    "priority": 0,
    "createdAt": "2022-05-24T13:36:42.449Z",
    "updatedAt": "2022-05-24T13:36:42.449Z",
    "paid": false
  },
  {
    "contentsId": 3505,
    "planetId": 4,
    "seriesId": 364,
    "thumbnailPath": "https://d2nmfrc2pe2bsk.cloudfront.net/1/1262/674ef99d-6cb3-4993-be3d-77871ea2224a.jpg?type=w100",
    "priority": 0,
    "createdAt": "2022-05-24T13:36:42.449Z",
    "updatedAt": "2022-05-24T13:36:42.449Z",
    "paid": false
  },
  {
    "contentsId": 3506,
    "planetId": 4,
    "seriesId": 364,
    "thumbnailPath": "https://d2nmfrc2pe2bsk.cloudfront.net/1/1262/39c45f95-1281-4dfd-9e03-0bea10c9480a.jpg?type=w100",
    "priority": 0,
    "createdAt": "2022-05-24T13:36:42.449Z",
    "updatedAt": "2022-05-24T13:36:42.449Z",
    "paid": false
  },
  {
    "contentsId": 3507,
    "planetId": 4,
    "seriesId": 364,
    "thumbnailPath": "https://d2nmfrc2pe2bsk.cloudfront.net/1/1262/18032226-c9c0-415b-94c8-4094442edcc8.jpg?type=w100",
    "priority": 0,
    "createdAt": "2022-05-24T13:36:42.449Z",
    "updatedAt": "2022-05-24T13:36:42.449Z",
    "paid": false
  },
  {
    "contentsId": 3508,
    "planetId": 4,
    "seriesId": 364,
    "thumbnailPath": "https://d2nmfrc2pe2bsk.cloudfront.net/1/1262/9b5cedba-6bdd-4d0b-ad5f-39a9e55e7575.jpg?type=w100",
    "priority": 0,
    "createdAt": "2022-05-24T13:36:42.449Z",
    "updatedAt": "2022-05-24T13:36:42.449Z",
    "paid": false
  },
  {
    "contentsId": 3509,
    "planetId": 4,
    "seriesId": 364,
    "thumbnailPath": "https://d2nmfrc2pe2bsk.cloudfront.net/1/1262/55b9db77-9a21-4712-8b98-81c7e60565d4.jpg?type=w100",
    "priority": 0,
    "createdAt": "2022-05-24T13:36:42.449Z",
    "updatedAt": "2022-05-24T13:36:42.449Z",
    "paid": false
  },
  {
    "contentsId": 3510,
    "planetId": 4,
    "seriesId": 364,
    "thumbnailPath": "https://d2nmfrc2pe2bsk.cloudfront.net/1/1262/cbbe7b4c-adff-4871-b117-f09fb68cc6dc.jpg?type=w100",
    "priority": 0,
    "createdAt": "2022-05-24T13:36:42.449Z",
    "updatedAt": "2022-05-24T13:36:42.449Z",
    "paid": false
  },
  {
    "contentsId": 3511,
    "planetId": 4,
    "seriesId": 364,
    "thumbnailPath": "https://d2nmfrc2pe2bsk.cloudfront.net/1/1262/95abdcbe-077c-4bcf-94ea-3c5c6d14826f.jpg?type=w100",
    "priority": 0,
    "createdAt": "2022-05-24T13:36:42.449Z",
    "updatedAt": "2022-05-24T13:36:42.449Z",
    "paid": false
  },
  {
    "contentsId": 3512,
    "planetId": 4,
    "seriesId": 364,
    "thumbnailPath": "https://d2nmfrc2pe2bsk.cloudfront.net/1/1262/d4cdc590-adee-44d6-995d-6c4ddea500be.jpg?type=w100",
    "priority": 0,
    "createdAt": "2022-05-24T13:36:42.449Z",
    "updatedAt": "2022-05-24T13:36:42.449Z",
    "paid": false
  }
]